par2/__init__.py
par2/__main__.py
par2/packets.py
par2/par2.py
par2/reader.py
par2py-0.1.2.dist-info/LICENSE
par2py-0.1.2.dist-info/METADATA
par2py-0.1.2.dist-info/WHEEL
par2py-0.1.2.dist-info/entry_points.txt
par2py-0.1.2.dist-info/top_level.txt
par2py-0.1.2.dist-info/zip-safe
par2py-0.1.2.dist-info/RECORD
