Metadata-Version: 2.1
Name: par2py
Version: 0.1.2
Summary: "par2 Python Utilities"
Home-page: http://github.com/EmperorArthur/par2py
Author: Arthur Moore
Author-email: arthur.moore.git@cd-net.net
License: MIT
Keywords: par2
Platform: UNKNOWN
Classifier: Development Status :: 3 - Alpha
Classifier: License :: OSI Approved :: MIT License
License-File: LICENSE
